macdefault.py
macdefault-1.0.1.dist-info/METADATA
macdefault-1.0.1.dist-info/WHEEL
macdefault-1.0.1.dist-info/entry_points.txt
macdefault-1.0.1.dist-info/licenses/LICENSE
macdefault-1.0.1.dist-info/RECORD
