Metadata-Version: 2.4
Name: macdefault
Version: 1.0.1
Summary: A macOS command-line utility for switching default file associations by file extension
Project-URL: Homepage, https://github.com/ac1982/macdefault
Project-URL: Repository, https://github.com/ac1982/macdefault
Project-URL: Issues, https://github.com/ac1982/macdefault/issues
Author: AC
License: MIT
License-File: LICENSE
Keywords: duti,file-associations,macos,office,utilities
Classifier: Development Status :: 4 - Beta
Classifier: Environment :: Console
Classifier: Intended Audience :: End Users/Desktop
Classifier: Operating System :: MacOS
Classifier: Programming Language :: Python :: 3.10
Classifier: Programming Language :: Python :: 3.11
Classifier: Programming Language :: Python :: 3.12
Classifier: Topic :: Utilities
Requires-Python: >=3.10
Requires-Dist: click>=8.0.0
Requires-Dist: questionary>=2.0.0
Requires-Dist: wcwidth>=0.2.0
